{"cameraMode":{"drawMode":0,"name":"Shaded","section":"Shading Mode"},"sceneLighting":true,"audioPlay":false,"sceneViewState":{"showFog":true,"showMaterialUpdate":false,"showSkybox":true,"showFlares":true,"showImageEffects":true,"showParticleSystems":true},"in2DMode":false,"pivot":{"x":-0.21806645393371583,"y":0.766437292098999,"z":0.007921218872070313},"rotation":{"x":-0.02048606239259243,"y":0.9677849411964417,"z":-0.08382370322942734,"w":-0.23652960360050202},"size":2.978620767593384,"orthographic":false}